git_vector/__init__.py
git_vector/git_vector.py
git_vector-0.1.0rc1.dist-info/LICENSE
git_vector-0.1.0rc1.dist-info/METADATA
git_vector-0.1.0rc1.dist-info/WHEEL
git_vector-0.1.0rc1.dist-info/entry_points.txt
git_vector-0.1.0rc1.dist-info/RECORD
