Metadata-Version: 2.1
Name: git-vector
Version: 0.1.0rc1
Summary: Prompt OpenAI models with git repository context
License: MIT
Author: Markus Blomqvist
Author-email: blomqvist_markus@hotmail.com
Requires-Python: >=3.11,<4.0
Classifier: License :: OSI Approved :: MIT License
Classifier: Programming Language :: Python :: 3
Classifier: Programming Language :: Python :: 3.11
Classifier: Programming Language :: Python :: 3.12
Classifier: Programming Language :: Python :: 3.13
Requires-Dist: click (>=8.1.7,<9.0.0)
Requires-Dist: gitpython (>=3.1.43,<4.0.0)
Requires-Dist: numpy (>=2.1.1,<3.0.0)
Requires-Dist: openai (>=1.47.1,<2.0.0)
Requires-Dist: python-dotenv (>=1.0.1,<2.0.0)
Requires-Dist: scikit-learn (>=1.5.2,<2.0.0)
Requires-Dist: tqdm (>=4.66.5,<5.0.0)
